pynab-0.6.7.dist-info/DESCRIPTION.rst
pynab-0.6.7.dist-info/METADATA
pynab-0.6.7.dist-info/metadata.json
pynab-0.6.7.dist-info/pbr.json
pynab-0.6.7.dist-info/RECORD
pynab-0.6.7.dist-info/top_level.txt
pynab-0.6.7.dist-info/WHEEL
ynab/__init__.py
ynab/_version.py
ynab/models.py
ynab/schema.py
ynab/util.py
ynab/ynab.py
