Metadata-Version: 2.0
Name: pynab
Version: 0.6.7
Summary: A minimalistic library designed to make it easy to access YNAB data from Python.
Home-page: http://github.com/aldanor/pynab
Author: Ivan Smirnov
Author-email: i.s.smirnov@gmail.com
License: UNKNOWN
Platform: UNKNOWN
Classifier: License :: OSI Approved :: BSD License
Classifier: Programming Language :: Python
Classifier: Programming Language :: Python :: 3
Requires-Dist: six
Requires-Dist: toolz
Requires-Dist: enum34
Requires-Dist: schematics
Requires-Dist: dateparser
